dvh/dvh.py
dvh/__init__.py
dvh-0.1.3.dist-info/DESCRIPTION.rst
dvh-0.1.3.dist-info/METADATA
dvh-0.1.3.dist-info/metadata.json
dvh-0.1.3.dist-info/RECORD
dvh-0.1.3.dist-info/top_level.txt
dvh-0.1.3.dist-info/WHEEL
